LICENSE
MANIFEST.in
README.md
setup.cfg
setup.py
src/os_fast_reservoir/VERSION
src/os_fast_reservoir/__init__.py
src/os_fast_reservoir/cmdline.py
src/os_fast_reservoir/reservoir.py
src/os_fast_reservoir.egg-info/PKG-INFO
src/os_fast_reservoir.egg-info/SOURCES.txt
src/os_fast_reservoir.egg-info/dependency_links.txt
src/os_fast_reservoir.egg-info/entry_points.txt
src/os_fast_reservoir.egg-info/not-zip-safe
src/os_fast_reservoir.egg-info/top_level.txt
tests/__init__.py
tests/test_cmdline.py
tests/test_sample.py