Metadata-Version: 1.1
Name: os-fast-reservoir
Version: 0.2.3
Summary: Python implementation of fast approximation reservioir sampling.
Home-page: https://github.com/cfhamlet/os-fast-reservoir
Author: Ozzy
Author-email: cfhamlet@gmail.com
License: MIT License
Platform: UNKNOWN
Classifier: Development Status :: 2 - Pre-Alpha
Classifier: Intended Audience :: Developers
Classifier: License :: OSI Approved :: MIT License
Classifier: Natural Language :: English
Classifier: Programming Language :: Python :: 2
Classifier: Programming Language :: Python :: 2.7
Classifier: Programming Language :: Python :: 3
Classifier: Programming Language :: Python :: 3.6
